me7_ba11/__init__.py
me7_ba11/__main__.py
me7_ba11/__version__.py
me7_ba11/exceptions.py
me7_ba11/meatball.py
me7_ba11/test.py
me7_ba11/config/__init__.py
me7_ba11/config/config.py
me7_ba11/config/config.yaml
me7_ba11/encrypt/__init__.py
me7_ba11/encrypt/encrypt.py
me7_ba11/manage/__init__.py
me7_ba11/manage/manager.py
me7_ba11/structs/__init__.py
me7_ba11/structs/objects.py
me7_ba11-1.0.dist-info/LICENSE
me7_ba11-1.0.dist-info/METADATA
me7_ba11-1.0.dist-info/WHEEL
me7_ba11-1.0.dist-info/top_level.txt
me7_ba11-1.0.dist-info/RECORD
