Metadata-Version: 2.1
Name: me7-ba11
Version: 1.0
Summary: light file management lib for line ctf 2022
Home-page: https://github.com/ppkill00/meat_ball
Author: jiho.park
Author-email: wulfsek@gmail.com
License: MIT
Download-URL: https://github.com/ppkill00/meat_ball/archive/master.zip
Keywords: pypi me7_ba11
Platform: UNKNOWN
Classifier: License :: OSI Approved :: MIT License
Classifier: Programming Language :: Python :: 3
Classifier: Programming Language :: Python :: 3.2
Classifier: Programming Language :: Python :: 3.3
Classifier: Programming Language :: Python :: 3.4
Classifier: Programming Language :: Python :: 3.5
Classifier: Programming Language :: Python :: 3.6
Classifier: Programming Language :: Python :: 3.7
Classifier: Programming Language :: Python :: 3.8
Classifier: Programming Language :: Python :: 3.9
Requires-Python: >=3
